README.md
setup.py
src/ssfinetuning/__init__.py
src/ssfinetuning/dataset_utils.py
src/ssfinetuning/default_args.py
src/ssfinetuning/models.py
src/ssfinetuning/plotting_utils.py
src/ssfinetuning/trainer_util.py
src/ssfinetuning/training_args.py
src/ssfinetuning.egg-info/PKG-INFO
src/ssfinetuning.egg-info/SOURCES.txt
src/ssfinetuning.egg-info/dependency_links.txt
src/ssfinetuning.egg-info/requires.txt
src/ssfinetuning.egg-info/top_level.txt