Metadata-Version: 2.1
Name: ssfinetuning
Version: 0.1.0
Summary: A package for fine tuning of pretrained NLP transformers using Semi Supervised Learning
Home-page: https://github.com/Ankush7890/ssfinetuning
Author: Ankush Checkervarty
Author-email: ankushc48@gmail.com
License: UNKNOWN
Keywords: NLP transformers huggingface deep learning pytorch
Platform: UNKNOWN
Classifier: Intended Audience :: Developers
Classifier: Intended Audience :: Education
Classifier: Intended Audience :: Science/Research
Classifier: License :: OSI Approved :: MIT License
Classifier: Operating System :: OS Independent
Classifier: Programming Language :: Python :: 3
Classifier: Programming Language :: Python :: 3.6
Classifier: Programming Language :: Python :: 3.8
Classifier: Topic :: Scientific/Engineering :: Artificial Intelligence
Requires-Python: >=3.6.0
